django_payments_yookassa/__init__.py
django_payments_yookassa/models.py
django_payments_yookassa/provider.py
django_payments_yookassa-0.1.1.dist-info/licenses/LICENSE
django_payments_yookassa-0.1.1.dist-info/METADATA
django_payments_yookassa-0.1.1.dist-info/WHEEL
django_payments_yookassa-0.1.1.dist-info/top_level.txt
django_payments_yookassa-0.1.1.dist-info/RECORD
