Metadata-Version: 2.4
Name: django-payments-yookassa
Version: 0.1.1
Summary: YooKassa payment provider for django-payments
Author-email: Ilia Bukin <your.email@example.com>
License: MIT
Project-URL: Homepage, https://github.com/iliab1/django-payments-yookassa
Project-URL: Issues, https://github.com/iliab1/django-payments-yookassa/issues
Requires-Python: >=3.10
License-File: LICENSE
Requires-Dist: yookassa>=3.5.0
Requires-Dist: django-payments>=3.0.1
Dynamic: license-file
